mailblaster/__init__.py
mailblaster/mailblaster.py
mailblaster-0.0.4.dist-info/LICENSE
mailblaster-0.0.4.dist-info/METADATA
mailblaster-0.0.4.dist-info/WHEEL
mailblaster-0.0.4.dist-info/top_level.txt
mailblaster-0.0.4.dist-info/RECORD
