Metadata-Version: 2.1
Name: mailblaster
Version: 0.0.4
Summary: Send many emails from many accounts
Home-page: https://github.com/prim4t/mailblaster
Author: prim4t
Author-email: python@prim4t.art
License-File: LICENSE
